README.md
setup.cfg
setup.py
DataExtruder/__init__.py
DataExtruder/datasource.py
DataExtruder/datasource_directus.py
DataExtruder/helper.py
DataExtruder/render_data.py
DataExtruder.egg-info/PKG-INFO
DataExtruder.egg-info/SOURCES.txt
DataExtruder.egg-info/dependency_links.txt
DataExtruder.egg-info/requires.txt
DataExtruder.egg-info/top_level.txt
DataExtruder/directus_api/__init__.py
DataExtruder/directus_api/directus.py
DataExtruder/directus_api/exceptions.py
DataExtruder/directus_api/models.py
DataExtruder/directus_api/utils/__init__.py
DataExtruder/directus_api/utils/apiclient.py
bin/dataextruder