Metadata-Version: 2.1
Name: DataExtruder
Version: 0.1.3
Summary: Render data from diffrent data-sources and jinaj2 template
Home-page: https://github.com/derBroBro/DataExtruder
Author: Malte Brodersen
Author-email: malte.brodersen@exoit.de
License: MIT
Download-URL: https://github.com/user/reponame/archive/v_01.tar.gz
Keywords: jinja2,directus
Platform: UNKNOWN
Classifier: Development Status :: 3 - Alpha
Classifier: Intended Audience :: Developers
Classifier: Topic :: Software Development :: Build Tools
Classifier: License :: OSI Approved :: MIT License
Classifier: Programming Language :: Python :: 3.7
